AUTHORS.rst
CONTRIBUTING.rst
HISTORY.rst
LICENSE
MANIFEST.in
README.rst
setup.cfg
setup.py
bsec_datastore.egg-info/PKG-INFO
bsec_datastore.egg-info/SOURCES.txt
bsec_datastore.egg-info/dependency_links.txt
bsec_datastore.egg-info/not-zip-safe
bsec_datastore.egg-info/top_level.txt
datastore/__init__.py
datastore/datastore.py
datastore/api/__init__.py
datastore/api/data.py
datastore/data/__init__.py
datastore/data/kuzushiji.py
datastore/data/p3b3.py
datastore/data/random.py
datastore/data/uno.py
datastore/sampling/__init__.py
datastore/sampling/bootstrap.py
datastore/sampling/cross_validation.py
datastore/utils/__init__.py
datastore/utils/utils.py
test/__init__.py
test/test_datastore.py