Metadata-Version: 1.1
Name: bsec-datastore
Version: 0.2.6
Summary: Data store for Bthe BSEC Pilot 3 program.
Home-page: https://github.com/yngtodd/datastore
Author: Todd Young
Author-email: youngmt1@ornl.gov
License: MIT
Keywords: datastore
Platform: UNKNOWN
Classifier: Development Status :: 2 - Pre-Alpha
Classifier: Intended Audience :: Developers
Classifier: License :: OSI Approved :: MIT License
Classifier: Natural Language :: English
Classifier: Programming Language :: Python :: 3.6
Classifier: Programming Language :: Python :: Implementation :: PyPy
